pymite/utils.py
pymite/__init__.py
pymite/mite.py
pymite/adapters.py
pymite-1.0.1.dist-info/top_level.txt
pymite-1.0.1.dist-info/METADATA
pymite-1.0.1.dist-info/DESCRIPTION.rst
pymite-1.0.1.dist-info/metadata.json
pymite-1.0.1.dist-info/WHEEL
pymite-1.0.1.dist-info/RECORD
