Metadata-Version: 2.0
Name: pymite
Version: 1.0.1
Summary: Python client for Mite.yo.lk time tracking service
Home-page: https://damnit.github.io/pymite/
Author: Otto Hockel
Author-email: hockel.otto@gmail.com
License: MIT
Keywords: mite,pymite,time tracking,time,tracking,mite.yo.lk
Platform: Posix; MacOS X; Windows
Classifier: Development Status :: 5 - Production/Stable
Classifier: Intended Audience :: Developers
Classifier: Operating System :: OS Independent
Classifier: Topic :: Internet
Classifier: Programming Language :: Python :: 3
Classifier: Programming Language :: Python :: 3.3
Classifier: Programming Language :: Python :: 3.4
Classifier: Programming Language :: Python :: 3.5
